pap_logger/__init__.py
pap_logger/__main__.py
pap_logger-0.0.9.dist-info/LICENSE
pap_logger-0.0.9.dist-info/METADATA
pap_logger-0.0.9.dist-info/WHEEL
pap_logger-0.0.9.dist-info/top_level.txt
pap_logger-0.0.9.dist-info/RECORD
