Metadata-Version: 2.1
Name: pap_logger
Version: 0.0.9
Summary: A 'prêt-à-porter' logger
Home-page: https://github.com/KurisuD/pap_logger
Author: KurisuD
Author-email: KurisuD@pypi.darnand.net
License: UNKNOWN
Platform: UNKNOWN
Classifier: Programming Language :: Python :: 3 :: Only
Classifier: Programming Language :: Python :: 3.5
Classifier: License :: Public Domain
Classifier: Operating System :: OS Independent
Classifier: Topic :: System :: Logging
